CHANGES.rst
CONTRIBUTORS.rst
DEVELOP.rst
LICENSE.rst
MANIFEST.in
README.rst
setup.cfg
setup.py
docs/conf.so
docs/index.rst
src/collective/__init__.py
src/collective.resume.egg-info/PKG-INFO
src/collective.resume.egg-info/SOURCES.txt
src/collective.resume.egg-info/dependency_links.txt
src/collective.resume.egg-info/entry_points.txt
src/collective.resume.egg-info/namespace_packages.txt
src/collective.resume.egg-info/not-zip-safe
src/collective.resume.egg-info/requires.txt
src/collective.resume.egg-info/top_level.txt
src/collective/resume/__init__.py
src/collective/resume/configure.zcml
src/collective/resume/interfaces.pyc
src/collective/resume/permissions.zcml
src/collective/resume/setuphandlers.pyc
src/collective/resume/subscribers.so
src/collective/resume/subscribers.zcml
src/collective/resume/testing.so
src/collective/resume/upgrades.so
src/collective/resume/upgrades.zcml
src/collective/resume/adapters/__init__.py
src/collective/resume/adapters/configure.zcml
src/collective/resume/adapters/typing.so
src/collective/resume/browser/__init__.py
src/collective/resume/browser/configure.zcml
src/collective/resume/browser/controlpanel.so
src/collective/resume/browser/overrides/.gitkeep
src/collective/resume/browser/static/.gitkeep
src/collective/resume/handlers/__init__.py
src/collective/resume/handlers/anything.so
src/collective/resume/handlers/configure.zcml
src/collective/resume/locales/README.rst
src/collective/resume/locales/__init__.py
src/collective/resume/locales/update.so
src/collective/resume/locales/en/LC_MESSAGES/collective.resume.mo
src/collective/resume/locales/zh_CN/LC_MESSAGES/collective.resume.mo
src/collective/resume/plugins/__init__.py
src/collective/resume/plugins/anything.so
src/collective/resume/plugins/cnv.so
src/collective/resume/plugins/configure.zcml
src/collective/resume/plugins/typing.so
src/collective/resume/profiles/default/browserlayer.xml
src/collective/resume/profiles/default/catalog.xml
src/collective/resume/profiles/default/metadata.xml
src/collective/resume/profiles/default/registry.xml
src/collective/resume/profiles/default/rolemap.xml
src/collective/resume/profiles/uninstall/browserlayer.xml
src/collective/resume/tests/__init__.py
src/collective/resume/tests/test_robot.so
src/collective/resume/tests/test_setup.so
src/collective/resume/tests/robot/test_example.robot
